[
    {
        "CategoryID": 593919879,
        "CategoryName": "aVgTFQmRZwtzOvf",
        "ProductName": "rlXApDwCTvAEecNiNrSAKprWOxIAFijf",
        "ProductSales": 16263498063.1992
    },
    {
        "CategoryID": 73459797,
        "CategoryName": "AzEURIiWkOKyEct",
        "ProductName": "NPQnTdvPkAhWHCDyeiBTkdNDjorPTGia",
        "ProductSales": 23850193154.0667
    },
    {
        "CategoryID": 1198002280,
        "CategoryName": "tIzSdRqhkUeZdkT",
        "ProductName": "MfSWVDvDamJdzUhnNqLjtQlWbLtKYvLL",
        "ProductSales": 35095181362.7034
    },
    {
        "CategoryID": 212214525,
        "CategoryName": "ygHVIQfoglSviry",
        "ProductName": "EZCBEYLtkdPAkRiWBySkJqwWIxkRpZmT",
        "ProductSales": 86836581840.1798
    },
    {
        "CategoryID": 286914757,
        "CategoryName": "KzwohgtywwWKMgK",
        "ProductName": "IxmhlYQXezzKMJSZesxnCTxYaoGlbBlg",
        "ProductSales": 7039157883.2641
    },
    {
        "CategoryID": 150592969,
        "CategoryName": "mSMlyDETAIhwRxO",
        "ProductName": "GYdTwgRfNBhXwVzbxqUuqoTpDUgjXGXS",
        "ProductSales": 65015715011.3955
    },
    {
        "CategoryID": 1893401026,
        "CategoryName": "uHqobZPheqNLxFe",
        "ProductName": "AtlISSDbHglbayQOnwFZUQpxJAxyYKdc",
        "ProductSales": 836937758.1402
    },
    {
        "CategoryID": 239261206,
        "CategoryName": "cwzgBcdpokrhKyS",
        "ProductName": "FAnULFzLiZGnCfWXOsuLZjEnNbvvjJWe",
        "ProductSales": 69037259207.1071
    },
    {
        "CategoryID": 1043807779,
        "CategoryName": "yQcYpnHnkbRgXWZ",
        "ProductName": "aGvFJRmTBqPUsaaGXGsxMuDcMQWOUpMl",
        "ProductSales": 64738057227.8052
    },
    {
        "CategoryID": 29407087,
        "CategoryName": "WJSaDRlVKTsdEtl",
        "ProductName": "LMQqAXJaQdBKrNmIZpaQGuRGUQIJftDL",
        "ProductSales": 21353499987.1626
    },
    {
        "CategoryID": 963107987,
        "CategoryName": "IJQacWWCECRNizI",
        "ProductName": "VhkhziMLffVIVFHrLwMiHcIyouXjnyJu",
        "ProductSales": 535684404.8947
    },
    {
        "CategoryID": 1432576217,
        "CategoryName": "hFVNjTVoDXgkVKJ",
        "ProductName": "UnsEuOWnIKDbsjdkFTltZqWfJPJxzTcv",
        "ProductSales": 23134835599.9216
    },
    {
        "CategoryID": 1637133068,
        "CategoryName": "naFguQzWpDQEILM",
        "ProductName": "FZwRfNkQZCnCwbGVNZfYnpeFBrBmWGkK",
        "ProductSales": 69519958505.4069
    },
    {
        "CategoryID": 387146064,
        "CategoryName": "YpZpBxYAmkSnhfg",
        "ProductName": "IOJvIPLOxWbrQiIfVCXYRZZpECYPmycZ",
        "ProductSales": 13471330143.5112
    },
    {
        "CategoryID": 1208164392,
        "CategoryName": "LhZXXjyIBURLlBv",
        "ProductName": "yEGbeLxmBMzUlRHsQFTUtRkBgNnTIdhK",
        "ProductSales": 42423913045.7863
    },
    {
        "CategoryID": 1335307210,
        "CategoryName": "thkYBvkkZkRmUEx",
        "ProductName": "kdqYEGwERlMiXpxPzENDvLPYkqchExYe",
        "ProductSales": 13665221049.4503
    },
    {
        "CategoryID": 2087530179,
        "CategoryName": "JeUBmQNvvniBtGN",
        "ProductName": "GkUaedNprOhpIrOkyFbqwftmdwYUCnuh",
        "ProductSales": 94396072695.963
    },
    {
        "CategoryID": 434978266,
        "CategoryName": "rCTetNCrmHqhXkI",
        "ProductName": "RhTONPsvdAvkUpAOFsEfVZwJtLLHgdGD",
        "ProductSales": 51093446929.0077
    },
    {
        "CategoryID": 407643647,
        "CategoryName": "sWYSCtdGomINbvT",
        "ProductName": "QAiOEEgbbePEKoYWFAGTDmqmQYmxcOWV",
        "ProductSales": 39573916513.4727
    },
    {
        "CategoryID": 806205857,
        "CategoryName": "BxryANALWxRhIVI",
        "ProductName": "EWofqQHIUiUUGUYmhsTYttTjeMMhdNew",
        "ProductSales": 43537935265.3399
    }
]